liusch/__init__.py
liusch/cache.py
liusch/data_fetcher.py
liusch/logger.py
liusch/main.py
liusch/schedule.py
liusch-1.0.5.dist-info/LICENSE
liusch-1.0.5.dist-info/METADATA
liusch-1.0.5.dist-info/WHEEL
liusch-1.0.5.dist-info/entry_points.txt
liusch-1.0.5.dist-info/top_level.txt
liusch-1.0.5.dist-info/RECORD
