Metadata-Version: 2.1
Name: liusch
Version: 1.0.5
License-File: LICENSE
Requires-Dist: requests
